[
  {
    "marque": "coucou",
    "model": "la",
    "quantite": 1,
    "emplacement": "aa",
    "unites": [
      {
        "numserie": "france",
        "position": "aa",
        "etatcvi": "non",
        "dateFinCVI": null
      }
    ],
    "createdAt": "2025-06-11T21:21:50.606Z"
  },
  {
    "marque": "zde",
    "model": "dzed",
    "quantite": 1,
    "emplacement": "",
    "unites": [
      {
        "numserie": "zed",
        "position": "",
        "etatcvi": "non",
        "dateFinCVI": null
      }
    ],
    "createdAt": "2025-06-11T21:23:49.554Z"
  },
  {
    "marque": "zed",
    "model": "dz",
    "quantite": 1,
    "emplacement": "",
    "unites": [
      {
        "numserie": "",
        "position": "",
        "etatcvi": "non",
        "dateFinCVI": null
      }
    ],
    "createdAt": "2025-06-11T21:27:58.205Z"
  },
  {
    "marque": "zcd",
    "model": "zdezdsz",
    "quantite": 1,
    "emplacement": "",
    "unites": [
      {
        "numserie": "dzed",
        "position": "",
        "etatcvi": "non",
        "dateFinCVI": null
      }
    ],
    "createdAt": "2025-06-11T21:34:59.170Z"
  },
  {
    "marque": "zszs",
    "model": "szszsz",
    "quantite": 1,
    "emplacement": "",
    "unites": [
      {
        "numserie": "zeszs",
        "position": "",
        "etatcvi": "non",
        "dateFinCVI": null
      }
    ],
    "createdAt": "2025-06-11T21:41:22.735Z"
  },
  {
    "marque": "ezrzf",
    "model": "dsfzfzd",
    "quantite": 1,
    "emplacement": "",
    "unites": [
      {
        "numserie": "zfecdzfs",
        "position": "",
        "etatcvi": "non",
        "dateFinCVI": null
      }
    ],
    "createdAt": "2025-06-11T21:46:07.011Z"
  },
  {
    "marque": "dzerzf",
    "model": "edfsfzs",
    "quantite": 1,
    "emplacement": "",
    "unites": [
      {
        "numserie": "ezfd",
        "position": "",
        "etatcvi": "non",
        "dateFinCVI": null
      }
    ],
    "createdAt": "2025-06-11T21:46:16.509Z"
  },
  {
    "marque": "dsc",
    "model": "csd",
    "quantite": 1,
    "emplacement": "",
    "unites": [
      {
        "numserie": "wcx",
        "position": "",
        "etatcvi": "non",
        "dateFinCVI": null
      }
    ],
    "createdAt": "2025-06-11T22:02:45.951Z"
  },
  {
    "marque": "kl",
    "model": "kjp,",
    "quantite": 1,
    "emplacement": "",
    "unites": [
      {
        "numserie": "ljkn",
        "position": "",
        "etatcvi": "non",
        "dateFinCVI": null
      }
    ],
    "createdAt": "2025-06-11T22:08:48.733Z"
  },
  {
    "marque": "qsd",
    "model": "qs",
    "quantite": 1,
    "emplacement": "",
    "unites": [
      {
        "numserie": "qsd",
        "position": "",
        "etatcvi": "non",
        "dateFinCVI": null
      }
    ],
    "createdAt": "2025-06-11T22:14:09.583Z"
  }
]